{
    "/js/app.min.js": "/js/app.min.js",
    "/js/revolving.min.js": "/js/revolving.min.js",
    "/css/app.min.css": "/css/app.min.css",
    "/images/create-track.png": "/images/create-track.png",
    "/images/dotted-bg.svg": "/images/dotted-bg.svg",
    "/images/logo-grey.svg": "/images/logo-grey.svg",
    "/images/logo-half.svg": "/images/logo-half.svg",
    "/images/logo-white.svg": "/images/logo-white.svg",
    "/images/logo.psd": "/images/logo.psd",
    "/images/logo.svg": "/images/logo.svg",
    "/images/mastercard.svg": "/images/mastercard.svg",
    "/images/payment.webp": "/images/payment.webp",
    "/images/rolling-dark.svg": "/images/rolling-dark.svg",
    "/images/rolling.svg": "/images/rolling.svg",
    "/images/stripe.svg": "/images/stripe.svg",
    "/images/visa.svg": "/images/visa.svg",
    "/images/wave-dark.svg": "/images/wave-dark.svg",
    "/images/wave-light.svg": "/images/wave-light.svg"
}
